module_qc_database_tools/__init__.py
module_qc_database_tools/_version.py
module_qc_database_tools/chip_config_api.py
module_qc_database_tools/core.py
module_qc_database_tools/exceptions.py
module_qc_database_tools/models.py
module_qc_database_tools/recycle.py
module_qc_database_tools/typing_compat.py
module_qc_database_tools/utils.py
module_qc_database_tools/cli/__init__.py
module_qc_database_tools/cli/__main__.py
module_qc_database_tools/cli/download_component.py
module_qc_database_tools/cli/fetch_reference_ivs.py
module_qc_database_tools/cli/generate_yarr_config.py
module_qc_database_tools/cli/get_bom_info.py
module_qc_database_tools/cli/get_vfd_info.py
module_qc_database_tools/cli/globals.py
module_qc_database_tools/cli/influxdbtool_retrieve.py
module_qc_database_tools/cli/localdbtool_retrieve.py
module_qc_database_tools/cli/localdbtool_upload.py
module_qc_database_tools/cli/main.py
module_qc_database_tools/cli/recycle_analysis.py
module_qc_database_tools/cli/recycle_esummary.py
module_qc_database_tools/cli/register_component.py
module_qc_database_tools/cli/review_component.py
module_qc_database_tools/cli/run_full_qc.py
module_qc_database_tools/cli/sync_component_stages.py
module_qc_database_tools/cli/upload_measurement.py
module_qc_database_tools/cli/utils.py
module_qc_database_tools/data/componentConfigs.json
module_qc_database_tools/data/YARR/chip_template.json
module_qc_database_tools/db/__init__.py
module_qc_database_tools/db/local.py
module_qc_database_tools/db/ls.py
module_qc_database_tools/db/prod.py
module_qc_database_tools/db/show_qc_pipeline.py
module_qc_database_tools/db/show_qc_status.py
module_qc_database_tools/db/show_test.py
module_qc_database_tools/db/upload_test.py
module_qc_database_tools/iv/__init__.py
module_qc_database_tools/iv/localdb.py
module_qc_database_tools/iv/proddb.py
module_qc_database_tools/review/__init__.py
module_qc_database_tools/review/checks.py
module_qc_database_tools/review/helpers.py
module_qc_database_tools-2.8.0.dist-info/METADATA
module_qc_database_tools-2.8.0.dist-info/WHEEL
module_qc_database_tools-2.8.0.dist-info/entry_points.txt
module_qc_database_tools-2.8.0.dist-info/licenses/LICENSE
module_qc_database_tools-2.8.0.dist-info/RECORD
