Metadata-Version: 2.4
Name: module-qc-database-tools
Version: 2.8.0
Summary: Python wrapper to interface with LocalDB and Production DB for common tasks for pixel modules.
Project-URL: Homepage, https://gitlab.cern.ch/atlas-itk/pixel/module/module-qc-database-tools
Project-URL: Bug Tracker, https://gitlab.cern.ch/atlas-itk/pixel/module/module-qc-database-tools/issues
Project-URL: Source, https://gitlab.cern.ch/atlas-itk/pixel/module/module-qc-database-tools
Project-URL: Documentation, https://atlas-itk-pixel-mqdbt.docs.cern.ch/2.8/
Author-email: Jay Chan <jay.chan@cern.ch>
Maintainer-email: Giordon Stark <kratsg@gmail.com>, Elisabetta Pianori <elisabetta.pianori@cern.ch>, Lingxin Meng <lingxin.meng@cern.ch>
License: Copyright (c) 2022 ATLAS ITk Pixel Modules
License-File: LICENSE
Classifier: Development Status :: 1 - Planning
Classifier: Intended Audience :: Developers
Classifier: Intended Audience :: Science/Research
Classifier: License :: OSI Approved :: MIT License
Classifier: Operating System :: OS Independent
Classifier: Programming Language :: Python
Classifier: Programming Language :: Python :: 3
Classifier: Programming Language :: Python :: 3 :: Only
Classifier: Programming Language :: Python :: 3.9
Classifier: Programming Language :: Python :: 3.10
Classifier: Programming Language :: Python :: 3.11
Classifier: Programming Language :: Python :: 3.12
Classifier: Programming Language :: Python :: 3.13
Classifier: Topic :: Scientific/Engineering
Requires-Python: >=3.9
Requires-Dist: arrow
Requires-Dist: cachecontrol<=0.14.1
Requires-Dist: influxdb
Requires-Dist: itkdb>=0.6.14
Requires-Dist: itksn>=0.4.2
Requires-Dist: jsbeautifier
Requires-Dist: jsondiff
Requires-Dist: module-qc-data-tools>=1.3.1
Requires-Dist: packaging
Requires-Dist: pandas
Requires-Dist: pyarrow
Requires-Dist: pymongo>=4.0.0
Requires-Dist: rich
Requires-Dist: typer
Requires-Dist: typing-extensions>=4.0; python_version < '3.10'
Requires-Dist: urllib3<2,>=1.26.20; 'el7.x86_64' in platform_release
